{"url":"https:\/\/hosting.iptvbillingsolution.com\/finalsca\/get-codes-list","method":"POST","isAJAX":true,"startTime":1662698046.605873,"totalTime":106.89999999999999,"totalMemory":"5.705","segmentDuration":20,"segmentCount":6,"CI_VERSION":"4.1.7","collectors":[{"title":"Timers","titleSafe":"timers","titleDetails":"","display":[],"badgeValue":null,"isEmpty":false,"hasTabContent":false,"hasLabel":false,"icon":"","hasTimelineData":true,"timelineData":[{"name":"Bootstrap","component":"Timer","start":1662698046.620398,"duration":0.012150049209594727},{"name":"Routing","component":"Timer","start":1662698046.63255,"duration":0.0002589225769042969},{"name":"Before Filters","component":"Timer","start":1662698046.633433,"duration":0.03614091873168945},{"name":"Controller","component":"Timer","start":1662698046.669582,"duration":0.04322409629821777},{"name":"Controller Constructor","component":"Timer","start":1662698046.669584,"duration":0.04032087326049805},{"name":"After Filters","component":"Timer","start":1662698046.712844,"duration":0.0007081031799316406}]},{"title":"Database","titleSafe":"database","titleDetails":"(9 total Queries, 7 of them unique across 1 Connection)","display":{"queries":[{"hover":"","class":"","duration":"1.29 ms","sql":"SHOW TABLES <strong>FROM<\/strong> `testingsca`","trace":[{"file":"SYSTEMPATH\/Database\/BaseConnection.php:1338","function":"\u00a0\u00a0\u00a0\u00a0\u00a0\u00a0\u00a0\u00a0CodeIgniter\\Database\\BaseConnection->query()","index":"\u00a0\u00a01\u00a0\u00a0\u00a0\u00a0"},{"file":"SYSTEMPATH\/Database\/BaseConnection.php:1369","function":"\u00a0\u00a0\u00a0\u00a0\u00a0\u00a0\u00a0\u00a0CodeIgniter\\Database\\BaseConnection->listTables()","index":"\u00a0\u00a02\u00a0\u00a0\u00a0\u00a0"},{"file":"APPPATH\/Filters\/isLoggedIn.php:29","function":"\u00a0\u00a0\u00a0\u00a0\u00a0\u00a0\u00a0\u00a0CodeIgniter\\Database\\BaseConnection->tableExists()","index":"\u00a0\u00a03\u00a0\u00a0\u00a0\u00a0"},{"file":"SYSTEMPATH\/Filters\/Filters.php:173","function":"\u00a0\u00a0\u00a0\u00a0\u00a0\u00a0\u00a0\u00a0App\\Filters\\isLoggedIn->before()","index":"\u00a0\u00a04\u00a0\u00a0\u00a0\u00a0"},{"file":"SYSTEMPATH\/CodeIgniter.php:386","function":"\u00a0\u00a0\u00a0\u00a0\u00a0\u00a0\u00a0\u00a0CodeIgniter\\Filters\\Filters->run()","index":"\u00a0\u00a05\u00a0\u00a0\u00a0\u00a0"},{"file":"SYSTEMPATH\/CodeIgniter.php:320","function":"\u00a0\u00a0\u00a0\u00a0\u00a0\u00a0\u00a0\u00a0CodeIgniter\\CodeIgniter->handleRequest()","index":"\u00a0\u00a06\u00a0\u00a0\u00a0\u00a0"},{"file":"FCPATH\/index.php:37","function":"\u00a0\u00a0\u00a0\u00a0\u00a0\u00a0\u00a0\u00a0CodeIgniter\\CodeIgniter->run()","index":"\u00a0\u00a07\u00a0\u00a0\u00a0\u00a0"}],"trace-file":"APPPATH\/Filters\/isLoggedIn.php:29","qid":"b7f292c149058aaefc09a08b70509036"},{"hover":"","class":"","duration":"17.71 ms","sql":"<strong>SELECT<\/strong> <strong>COUNT<\/strong>(*) <strong>AS<\/strong> `numrows`\n<strong>FROM<\/strong> `tbl_admin`","trace":[{"file":"SYSTEMPATH\/Database\/BaseBuilder.php:1539","function":"\u00a0\u00a0\u00a0\u00a0\u00a0\u00a0\u00a0\u00a0CodeIgniter\\Database\\BaseConnection->query()","index":"\u00a0\u00a01\u00a0\u00a0\u00a0\u00a0"},{"file":"APPPATH\/Filters\/isLoggedIn.php:31","function":"\u00a0\u00a0\u00a0\u00a0\u00a0\u00a0\u00a0\u00a0CodeIgniter\\Database\\BaseBuilder->countAllResults()","index":"\u00a0\u00a02\u00a0\u00a0\u00a0\u00a0"},{"file":"SYSTEMPATH\/Filters\/Filters.php:173","function":"\u00a0\u00a0\u00a0\u00a0\u00a0\u00a0\u00a0\u00a0App\\Filters\\isLoggedIn->before()","index":"\u00a0\u00a03\u00a0\u00a0\u00a0\u00a0"},{"file":"SYSTEMPATH\/CodeIgniter.php:386","function":"\u00a0\u00a0\u00a0\u00a0\u00a0\u00a0\u00a0\u00a0CodeIgniter\\Filters\\Filters->run()","index":"\u00a0\u00a04\u00a0\u00a0\u00a0\u00a0"},{"file":"SYSTEMPATH\/CodeIgniter.php:320","function":"\u00a0\u00a0\u00a0\u00a0\u00a0\u00a0\u00a0\u00a0CodeIgniter\\CodeIgniter->handleRequest()","index":"\u00a0\u00a05\u00a0\u00a0\u00a0\u00a0"},{"file":"FCPATH\/index.php:37","function":"\u00a0\u00a0\u00a0\u00a0\u00a0\u00a0\u00a0\u00a0CodeIgniter\\CodeIgniter->run()","index":"\u00a0\u00a06\u00a0\u00a0\u00a0\u00a0"}],"trace-file":"APPPATH\/Filters\/isLoggedIn.php:31","qid":"63be31e28b53f96a11b1501872b56d87"},{"hover":"","class":"","duration":"0.64 ms","sql":"<strong>SELECT<\/strong> *\n<strong>FROM<\/strong> `migrations`\n<strong>WHERE<\/strong> `namespace` = &#039;App&#039;\n<strong>ORDER<\/strong> <strong>BY<\/strong> `id` <strong>ASC<\/strong>","trace":[{"file":"SYSTEMPATH\/Database\/BaseBuilder.php:1455","function":"\u00a0\u00a0\u00a0\u00a0\u00a0\u00a0\u00a0\u00a0CodeIgniter\\Database\\BaseConnection->query()","index":"\u00a0\u00a01\u00a0\u00a0\u00a0\u00a0"},{"file":"SYSTEMPATH\/Database\/MigrationRunner.php:648","function":"\u00a0\u00a0\u00a0\u00a0\u00a0\u00a0\u00a0\u00a0CodeIgniter\\Database\\BaseBuilder->get()","index":"\u00a0\u00a02\u00a0\u00a0\u00a0\u00a0"},{"file":"SYSTEMPATH\/Database\/MigrationRunner.php:179","function":"\u00a0\u00a0\u00a0\u00a0\u00a0\u00a0\u00a0\u00a0CodeIgniter\\Database\\MigrationRunner->getHistory()","index":"\u00a0\u00a03\u00a0\u00a0\u00a0\u00a0"},{"file":"APPPATH\/Controllers\/BaseController.php:166","function":"\u00a0\u00a0\u00a0\u00a0\u00a0\u00a0\u00a0\u00a0CodeIgniter\\Database\\MigrationRunner->latest()","index":"\u00a0\u00a04\u00a0\u00a0\u00a0\u00a0"},{"file":"APPPATH\/Controllers\/BaseController.php:110","function":"\u00a0\u00a0\u00a0\u00a0\u00a0\u00a0\u00a0\u00a0App\\Controllers\\BaseController->checkdbconnection()","index":"\u00a0\u00a05\u00a0\u00a0\u00a0\u00a0"},{"file":"SYSTEMPATH\/CodeIgniter.php:803","function":"\u00a0\u00a0\u00a0\u00a0\u00a0\u00a0\u00a0\u00a0App\\Controllers\\BaseController->initController()","index":"\u00a0\u00a06\u00a0\u00a0\u00a0\u00a0"},{"file":"SYSTEMPATH\/CodeIgniter.php:403","function":"\u00a0\u00a0\u00a0\u00a0\u00a0\u00a0\u00a0\u00a0CodeIgniter\\CodeIgniter->createController()","index":"\u00a0\u00a07\u00a0\u00a0\u00a0\u00a0"},{"file":"SYSTEMPATH\/CodeIgniter.php:320","function":"\u00a0\u00a0\u00a0\u00a0\u00a0\u00a0\u00a0\u00a0CodeIgniter\\CodeIgniter->handleRequest()","index":"\u00a0\u00a08\u00a0\u00a0\u00a0\u00a0"},{"file":"FCPATH\/index.php:37","function":"\u00a0\u00a0\u00a0\u00a0\u00a0\u00a0\u00a0\u00a0CodeIgniter\\CodeIgniter->run()","index":"\u00a0\u00a09\u00a0\u00a0\u00a0\u00a0"}],"trace-file":"APPPATH\/Controllers\/BaseController.php:166","qid":"dafe61f6a25b1a2e40e3fbd0b361bdf5"},{"hover":"","class":"","duration":"0.2 ms","sql":"<strong>SELECT<\/strong> <strong>MAX<\/strong>(`batch`) <strong>AS<\/strong> `batch`\n<strong>FROM<\/strong> `migrations`","trace":[{"file":"SYSTEMPATH\/Database\/BaseBuilder.php:1455","function":"\u00a0\u00a0\u00a0\u00a0\u00a0\u00a0\u00a0\u00a0CodeIgniter\\Database\\BaseConnection->query()","index":"\u00a0\u00a01\u00a0\u00a0\u00a0\u00a0"},{"file":"SYSTEMPATH\/Database\/MigrationRunner.php:696","function":"\u00a0\u00a0\u00a0\u00a0\u00a0\u00a0\u00a0\u00a0CodeIgniter\\Database\\BaseBuilder->get()","index":"\u00a0\u00a02\u00a0\u00a0\u00a0\u00a0"},{"file":"SYSTEMPATH\/Database\/MigrationRunner.php:183","function":"\u00a0\u00a0\u00a0\u00a0\u00a0\u00a0\u00a0\u00a0CodeIgniter\\Database\\MigrationRunner->getLastBatch()","index":"\u00a0\u00a03\u00a0\u00a0\u00a0\u00a0"},{"file":"APPPATH\/Controllers\/BaseController.php:166","function":"\u00a0\u00a0\u00a0\u00a0\u00a0\u00a0\u00a0\u00a0CodeIgniter\\Database\\MigrationRunner->latest()","index":"\u00a0\u00a04\u00a0\u00a0\u00a0\u00a0"},{"file":"APPPATH\/Controllers\/BaseController.php:110","function":"\u00a0\u00a0\u00a0\u00a0\u00a0\u00a0\u00a0\u00a0App\\Controllers\\BaseController->checkdbconnection()","index":"\u00a0\u00a05\u00a0\u00a0\u00a0\u00a0"},{"file":"SYSTEMPATH\/CodeIgniter.php:803","function":"\u00a0\u00a0\u00a0\u00a0\u00a0\u00a0\u00a0\u00a0App\\Controllers\\BaseController->initController()","index":"\u00a0\u00a06\u00a0\u00a0\u00a0\u00a0"},{"file":"SYSTEMPATH\/CodeIgniter.php:403","function":"\u00a0\u00a0\u00a0\u00a0\u00a0\u00a0\u00a0\u00a0CodeIgniter\\CodeIgniter->createController()","index":"\u00a0\u00a07\u00a0\u00a0\u00a0\u00a0"},{"file":"SYSTEMPATH\/CodeIgniter.php:320","function":"\u00a0\u00a0\u00a0\u00a0\u00a0\u00a0\u00a0\u00a0CodeIgniter\\CodeIgniter->handleRequest()","index":"\u00a0\u00a08\u00a0\u00a0\u00a0\u00a0"},{"file":"FCPATH\/index.php:37","function":"\u00a0\u00a0\u00a0\u00a0\u00a0\u00a0\u00a0\u00a0CodeIgniter\\CodeIgniter->run()","index":"\u00a0\u00a09\u00a0\u00a0\u00a0\u00a0"}],"trace-file":"APPPATH\/Controllers\/BaseController.php:166","qid":"014840ad6bc65db680e1e03adcdd59dd"},{"hover":"This query was called more than once.","class":"duplicate","duration":"15.35 ms","sql":"<strong>SELECT<\/strong> <strong>COUNT<\/strong>(*) <strong>AS<\/strong> `numrows`\n<strong>FROM<\/strong> `tbl_admin`","trace":[{"file":"SYSTEMPATH\/Database\/BaseBuilder.php:1539","function":"\u00a0\u00a0\u00a0\u00a0\u00a0\u00a0\u00a0\u00a0CodeIgniter\\Database\\BaseConnection->query()","index":"\u00a0\u00a01\u00a0\u00a0\u00a0\u00a0"},{"file":"APPPATH\/Controllers\/BaseController.php:120","function":"\u00a0\u00a0\u00a0\u00a0\u00a0\u00a0\u00a0\u00a0CodeIgniter\\Database\\BaseBuilder->countAllResults()","index":"\u00a0\u00a02\u00a0\u00a0\u00a0\u00a0"},{"file":"SYSTEMPATH\/CodeIgniter.php:803","function":"\u00a0\u00a0\u00a0\u00a0\u00a0\u00a0\u00a0\u00a0App\\Controllers\\BaseController->initController()","index":"\u00a0\u00a03\u00a0\u00a0\u00a0\u00a0"},{"file":"SYSTEMPATH\/CodeIgniter.php:403","function":"\u00a0\u00a0\u00a0\u00a0\u00a0\u00a0\u00a0\u00a0CodeIgniter\\CodeIgniter->createController()","index":"\u00a0\u00a04\u00a0\u00a0\u00a0\u00a0"},{"file":"SYSTEMPATH\/CodeIgniter.php:320","function":"\u00a0\u00a0\u00a0\u00a0\u00a0\u00a0\u00a0\u00a0CodeIgniter\\CodeIgniter->handleRequest()","index":"\u00a0\u00a05\u00a0\u00a0\u00a0\u00a0"},{"file":"FCPATH\/index.php:37","function":"\u00a0\u00a0\u00a0\u00a0\u00a0\u00a0\u00a0\u00a0CodeIgniter\\CodeIgniter->run()","index":"\u00a0\u00a06\u00a0\u00a0\u00a0\u00a0"}],"trace-file":"APPPATH\/Controllers\/BaseController.php:120","qid":"62b53f21033275f5fa567242726a07f5"},{"hover":"This query was called more than once.","class":"duplicate","duration":"1.02 ms","sql":"<strong>SELECT<\/strong> <strong>COUNT<\/strong>(*) <strong>AS<\/strong> `numrows`\n<strong>FROM<\/strong> `tbl_admin`","trace":[{"file":"SYSTEMPATH\/Database\/BaseBuilder.php:1539","function":"\u00a0\u00a0\u00a0\u00a0\u00a0\u00a0\u00a0\u00a0CodeIgniter\\Database\\BaseConnection->query()","index":"\u00a0\u00a01\u00a0\u00a0\u00a0\u00a0"},{"file":"APPPATH\/Controllers\/BaseController.php:141","function":"\u00a0\u00a0\u00a0\u00a0\u00a0\u00a0\u00a0\u00a0CodeIgniter\\Database\\BaseBuilder->countAllResults()","index":"\u00a0\u00a02\u00a0\u00a0\u00a0\u00a0"},{"file":"SYSTEMPATH\/CodeIgniter.php:803","function":"\u00a0\u00a0\u00a0\u00a0\u00a0\u00a0\u00a0\u00a0App\\Controllers\\BaseController->initController()","index":"\u00a0\u00a03\u00a0\u00a0\u00a0\u00a0"},{"file":"SYSTEMPATH\/CodeIgniter.php:403","function":"\u00a0\u00a0\u00a0\u00a0\u00a0\u00a0\u00a0\u00a0CodeIgniter\\CodeIgniter->createController()","index":"\u00a0\u00a04\u00a0\u00a0\u00a0\u00a0"},{"file":"SYSTEMPATH\/CodeIgniter.php:320","function":"\u00a0\u00a0\u00a0\u00a0\u00a0\u00a0\u00a0\u00a0CodeIgniter\\CodeIgniter->handleRequest()","index":"\u00a0\u00a05\u00a0\u00a0\u00a0\u00a0"},{"file":"FCPATH\/index.php:37","function":"\u00a0\u00a0\u00a0\u00a0\u00a0\u00a0\u00a0\u00a0CodeIgniter\\CodeIgniter->run()","index":"\u00a0\u00a06\u00a0\u00a0\u00a0\u00a0"}],"trace-file":"APPPATH\/Controllers\/BaseController.php:141","qid":"dcbb005042b9695a05856c24a8fe4f33"},{"hover":"","class":"","duration":"2.2 ms","sql":"<strong>SELECT<\/strong> *, DATE_FORMAT(activationdate, &#039;%M %e, %Y&#039;) as formatted_activationdate, DATE_FORMAT(created_at, &#039;%M %e, %Y&#039;) as formatted_createddate\n<strong>FROM<\/strong> `tbl_codes`\n<strong>WHERE<\/strong> `file_id` = &#039;3&#039;\n<strong>ORDER<\/strong> <strong>BY<\/strong> `id` <strong>DESC<\/strong>","trace":[{"file":"SYSTEMPATH\/Database\/BaseBuilder.php:1455","function":"\u00a0\u00a0\u00a0\u00a0\u00a0\u00a0\u00a0\u00a0CodeIgniter\\Database\\BaseConnection->query()","index":"\u00a0\u00a01\u00a0\u00a0\u00a0\u00a0"},{"file":"SYSTEMPATH\/Model.php:728","function":"\u00a0\u00a0\u00a0\u00a0\u00a0\u00a0\u00a0\u00a0CodeIgniter\\Database\\BaseBuilder->get()","index":"\u00a0\u00a02\u00a0\u00a0\u00a0\u00a0"},{"file":"APPPATH\/Models\/Codemodel.php:207","function":"\u00a0\u00a0\u00a0\u00a0\u00a0\u00a0\u00a0\u00a0CodeIgniter\\Model->__call()","index":"\u00a0\u00a03\u00a0\u00a0\u00a0\u00a0"},{"file":"APPPATH\/Controllers\/Codes.php:449","function":"\u00a0\u00a0\u00a0\u00a0\u00a0\u00a0\u00a0\u00a0App\\Models\\Codemodel->dataifsearchnot()","index":"\u00a0\u00a04\u00a0\u00a0\u00a0\u00a0"},{"file":"SYSTEMPATH\/CodeIgniter.php:825","function":"\u00a0\u00a0\u00a0\u00a0\u00a0\u00a0\u00a0\u00a0App\\Controllers\\Codes->getcodeslist()","index":"\u00a0\u00a05\u00a0\u00a0\u00a0\u00a0"},{"file":"SYSTEMPATH\/CodeIgniter.php:412","function":"\u00a0\u00a0\u00a0\u00a0\u00a0\u00a0\u00a0\u00a0CodeIgniter\\CodeIgniter->runController()","index":"\u00a0\u00a06\u00a0\u00a0\u00a0\u00a0"},{"file":"SYSTEMPATH\/CodeIgniter.php:320","function":"\u00a0\u00a0\u00a0\u00a0\u00a0\u00a0\u00a0\u00a0CodeIgniter\\CodeIgniter->handleRequest()","index":"\u00a0\u00a07\u00a0\u00a0\u00a0\u00a0"},{"file":"FCPATH\/index.php:37","function":"\u00a0\u00a0\u00a0\u00a0\u00a0\u00a0\u00a0\u00a0CodeIgniter\\CodeIgniter->run()","index":"\u00a0\u00a08\u00a0\u00a0\u00a0\u00a0"}],"trace-file":"APPPATH\/Models\/Codemodel.php:207","qid":"a23fdf6e7a500862ec148dcdf2aa974b"},{"hover":"","class":"","duration":"0.32 ms","sql":"<strong>SELECT<\/strong> *, DATE_FORMAT(activationdate, &#039;%M %e, %Y&#039;) as formatted_activationdate, DATE_FORMAT(created_at, &#039;%M %e, %Y&#039;) as formatted_createddate\n<strong>FROM<\/strong> `tbl_codes`\n<strong>WHERE<\/strong> `file_id` = &#039;3&#039;\n<strong>ORDER<\/strong> <strong>BY<\/strong> `id` <strong>DESC<\/strong>\n <strong>LIMIT<\/strong> 10","trace":[{"file":"SYSTEMPATH\/Database\/BaseBuilder.php:1455","function":"\u00a0\u00a0\u00a0\u00a0\u00a0\u00a0\u00a0\u00a0CodeIgniter\\Database\\BaseConnection->query()","index":"\u00a0\u00a01\u00a0\u00a0\u00a0\u00a0"},{"file":"SYSTEMPATH\/Model.php:728","function":"\u00a0\u00a0\u00a0\u00a0\u00a0\u00a0\u00a0\u00a0CodeIgniter\\Database\\BaseBuilder->get()","index":"\u00a0\u00a02\u00a0\u00a0\u00a0\u00a0"},{"file":"APPPATH\/Models\/Codemodel.php:278","function":"\u00a0\u00a0\u00a0\u00a0\u00a0\u00a0\u00a0\u00a0CodeIgniter\\Model->__call()","index":"\u00a0\u00a03\u00a0\u00a0\u00a0\u00a0"},{"file":"APPPATH\/Controllers\/Codes.php:450","function":"\u00a0\u00a0\u00a0\u00a0\u00a0\u00a0\u00a0\u00a0App\\Models\\Codemodel->perpagedataifsearchnot()","index":"\u00a0\u00a04\u00a0\u00a0\u00a0\u00a0"},{"file":"SYSTEMPATH\/CodeIgniter.php:825","function":"\u00a0\u00a0\u00a0\u00a0\u00a0\u00a0\u00a0\u00a0App\\Controllers\\Codes->getcodeslist()","index":"\u00a0\u00a05\u00a0\u00a0\u00a0\u00a0"},{"file":"SYSTEMPATH\/CodeIgniter.php:412","function":"\u00a0\u00a0\u00a0\u00a0\u00a0\u00a0\u00a0\u00a0CodeIgniter\\CodeIgniter->runController()","index":"\u00a0\u00a06\u00a0\u00a0\u00a0\u00a0"},{"file":"SYSTEMPATH\/CodeIgniter.php:320","function":"\u00a0\u00a0\u00a0\u00a0\u00a0\u00a0\u00a0\u00a0CodeIgniter\\CodeIgniter->handleRequest()","index":"\u00a0\u00a07\u00a0\u00a0\u00a0\u00a0"},{"file":"FCPATH\/index.php:37","function":"\u00a0\u00a0\u00a0\u00a0\u00a0\u00a0\u00a0\u00a0CodeIgniter\\CodeIgniter->run()","index":"\u00a0\u00a08\u00a0\u00a0\u00a0\u00a0"}],"trace-file":"APPPATH\/Models\/Codemodel.php:278","qid":"1b3eaf82f558882c7b1779b3903887c7"},{"hover":"","class":"","duration":"0.16 ms","sql":"<strong>SELECT<\/strong> *\n<strong>FROM<\/strong> `tbl_license`","trace":[{"file":"SYSTEMPATH\/Database\/BaseBuilder.php:1455","function":"\u00a0\u00a0\u00a0\u00a0\u00a0\u00a0\u00a0\u00a0CodeIgniter\\Database\\BaseConnection->query()","index":"\u00a0\u00a01\u00a0\u00a0\u00a0\u00a0"},{"file":"SYSTEMPATH\/Model.php:728","function":"\u00a0\u00a0\u00a0\u00a0\u00a0\u00a0\u00a0\u00a0CodeIgniter\\Database\\BaseBuilder->get()","index":"\u00a0\u00a02\u00a0\u00a0\u00a0\u00a0"},{"file":"APPPATH\/Controllers\/BaseController.php:364","function":"\u00a0\u00a0\u00a0\u00a0\u00a0\u00a0\u00a0\u00a0CodeIgniter\\Model->__call()","index":"\u00a0\u00a03\u00a0\u00a0\u00a0\u00a0"},{"file":"APPPATH\/Filters\/isLoggedIn.php:57","function":"\u00a0\u00a0\u00a0\u00a0\u00a0\u00a0\u00a0\u00a0App\\Controllers\\BaseController->sca_dochecklicense()","index":"\u00a0\u00a04\u00a0\u00a0\u00a0\u00a0"},{"file":"SYSTEMPATH\/Filters\/Filters.php:196","function":"\u00a0\u00a0\u00a0\u00a0\u00a0\u00a0\u00a0\u00a0App\\Filters\\isLoggedIn->after()","index":"\u00a0\u00a05\u00a0\u00a0\u00a0\u00a0"},{"file":"SYSTEMPATH\/CodeIgniter.php:429","function":"\u00a0\u00a0\u00a0\u00a0\u00a0\u00a0\u00a0\u00a0CodeIgniter\\Filters\\Filters->run()","index":"\u00a0\u00a06\u00a0\u00a0\u00a0\u00a0"},{"file":"SYSTEMPATH\/CodeIgniter.php:320","function":"\u00a0\u00a0\u00a0\u00a0\u00a0\u00a0\u00a0\u00a0CodeIgniter\\CodeIgniter->handleRequest()","index":"\u00a0\u00a07\u00a0\u00a0\u00a0\u00a0"},{"file":"FCPATH\/index.php:37","function":"\u00a0\u00a0\u00a0\u00a0\u00a0\u00a0\u00a0\u00a0CodeIgniter\\CodeIgniter->run()","index":"\u00a0\u00a08\u00a0\u00a0\u00a0\u00a0"}],"trace-file":"APPPATH\/Controllers\/BaseController.php:364","qid":"206c3df671c89df012bb2e968860416a"}]},"badgeValue":9,"isEmpty":false,"hasTabContent":true,"hasLabel":false,"icon":"data:image\/png;base64,iVBORw0KGgoAAAANSUhEUgAAABgAAAAYCAYAAADgdz34AAAAAXNSR0IArs4c6QAAAARnQU1BAACxjwv8YQUAAAAJcEhZcwAADsMAAA7DAcdvqGQAAADMSURBVEhLY6A3YExLSwsA4nIycQDIDIhRWEBqamo\/UNF\/SjDQjF6ocZgAKPkRiFeEhoYyQ4WIBiA9QAuWAPEHqBAmgLqgHcolGQD1V4DMgHIxwbCxYD+QBqcKINseKo6eWrBioPrtQBq\/BcgY5ht0cUIYbBg2AJKkRxCNWkDQgtFUNJwtABr+F6igE8olGQD114HMgHIxAVDyAhA\/AlpSA8RYUwoeXAPVex5qHCbIyMgwBCkAuQJIY00huDBUz\/mUlBQDqHGjgBjAwAAACexpph6oHSQAAAAASUVORK5CYII=","hasTimelineData":true,"timelineData":[{"name":"Connecting to Database: \"default\"","component":"Database","start":1662698046.640788,"duration":"0.002821"},{"name":"Query","component":"Database","start":1662698046.644068,"duration":"0.001290","query":"SHOW TABLES <strong>FROM<\/strong> `testingsca`"},{"name":"Query","component":"Database","start":1662698046.651682,"duration":"0.017705","query":"<strong>SELECT<\/strong> <strong>COUNT<\/strong>(*) <strong>AS<\/strong> `numrows`\n<strong>FROM<\/strong> `tbl_admin`"},{"name":"Query","component":"Database","start":1662698046.692145,"duration":"0.000644","query":"<strong>SELECT<\/strong> *\n<strong>FROM<\/strong> `migrations`\n<strong>WHERE<\/strong> `namespace` = &#039;App&#039;\n<strong>ORDER<\/strong> <strong>BY<\/strong> `id` <strong>ASC<\/strong>"},{"name":"Query","component":"Database","start":1662698046.69292,"duration":"0.000197","query":"<strong>SELECT<\/strong> <strong>MAX<\/strong>(`batch`) <strong>AS<\/strong> `batch`\n<strong>FROM<\/strong> `migrations`"},{"name":"Query","component":"Database","start":1662698046.693174,"duration":"0.015353","query":"<strong>SELECT<\/strong> <strong>COUNT<\/strong>(*) <strong>AS<\/strong> `numrows`\n<strong>FROM<\/strong> `tbl_admin`"},{"name":"Query","component":"Database","start":1662698046.708802,"duration":"0.001021","query":"<strong>SELECT<\/strong> <strong>COUNT<\/strong>(*) <strong>AS<\/strong> `numrows`\n<strong>FROM<\/strong> `tbl_admin`"},{"name":"Query","component":"Database","start":1662698046.710085,"duration":"0.002200","query":"<strong>SELECT<\/strong> *, DATE_FORMAT(activationdate, &#039;%M %e, %Y&#039;) as formatted_activationdate, DATE_FORMAT(created_at, &#039;%M %e, %Y&#039;) as formatted_createddate\n<strong>FROM<\/strong> `tbl_codes`\n<strong>WHERE<\/strong> `file_id` = &#039;3&#039;\n<strong>ORDER<\/strong> <strong>BY<\/strong> `id` <strong>DESC<\/strong>"},{"name":"Query","component":"Database","start":1662698046.712419,"duration":"0.000319","query":"<strong>SELECT<\/strong> *, DATE_FORMAT(activationdate, &#039;%M %e, %Y&#039;) as formatted_activationdate, DATE_FORMAT(created_at, &#039;%M %e, %Y&#039;) as formatted_createddate\n<strong>FROM<\/strong> `tbl_codes`\n<strong>WHERE<\/strong> `file_id` = &#039;3&#039;\n<strong>ORDER<\/strong> <strong>BY<\/strong> `id` <strong>DESC<\/strong>\n <strong>LIMIT<\/strong> 10"},{"name":"Query","component":"Database","start":1662698046.712914,"duration":"0.000159","query":"<strong>SELECT<\/strong> *\n<strong>FROM<\/strong> `tbl_license`"}]},{"title":"Logs","titleSafe":"logs","titleDetails":"","display":{"logs":[]},"badgeValue":null,"isEmpty":true,"hasTabContent":true,"hasLabel":false,"icon":"data:image\/png;base64,iVBORw0KGgoAAAANSUhEUgAAABgAAAAYCAYAAADgdz34AAAAAXNSR0IArs4c6QAAAARnQU1BAACxjwv8YQUAAAAJcEhZcwAADsMAAA7DAcdvqGQAAACYSURBVEhLYxgFJIHU1FSjtLS0i0D8AYj7gEKMEBkqAaAFF4D4ERCvAFrwH4gDoFIMKSkpFkB+OTEYqgUTACXfA\/GqjIwMQyD9H2hRHlQKJFcBEiMGQ7VgAqCBvUgK32dmZspCpagGGNPT0\/1BLqeF4bQHQJePpiIwhmrBBEADR1MRfgB0+WgqAmOoFkwANHA0FY0CUgEDAwCQ0PUpNB3kqwAAAABJRU5ErkJggg==","hasTimelineData":false,"timelineData":[]},{"title":"Views","titleSafe":"views","titleDetails":"","display":[],"badgeValue":0,"isEmpty":false,"hasTabContent":false,"hasLabel":true,"icon":"data:image\/png;base64,iVBORw0KGgoAAAANSUhEUgAAABgAAAAYCAYAAADgdz34AAAAAXNSR0IArs4c6QAAAARnQU1BAACxjwv8YQUAAAAJcEhZcwAADsMAAA7DAcdvqGQAAADeSURBVEhL7ZSxDcIwEEWNYA0YgGmgyAaJLTcUaaBzQQEVjMEabBQxAdw53zTHiThEovGTfnE\/9rsoRUxhKLOmaa6Uh7X2+UvguLCzVxN1XW9x4EYHzik033Hp3X0LO+DaQG8MDQcuq6qao4qkHuMgQggLvkPLjqh00ZgFDBacMJYFkuwFlH1mshdkZ5JPJERA9JpI6xNCBESvibQ+IURA9JpI6xNCBESvibQ+IURA9DTsuHTOrVFFxixgB\/eUFlU8uKJ0eDBFOu\/9EvoeKnlJS2\/08Tc8NOwQ8sIfMeYFjqKDjdU2sp4AAAAASUVORK5CYII=","hasTimelineData":true,"timelineData":[]},{"title":"Files","titleSafe":"files","titleDetails":"( 154 )","display":{"coreFiles":[{"name":"AutoloadConfig.php","path":"SYSTEMPATH\/Config\/AutoloadConfig.php"},{"name":"Autoloader.php","path":"SYSTEMPATH\/Autoloader\/Autoloader.php"},{"name":"BaseBuilder.php","path":"SYSTEMPATH\/Database\/BaseBuilder.php"},{"name":"BaseCollector.php","path":"SYSTEMPATH\/Debug\/Toolbar\/Collectors\/BaseCollector.php"},{"name":"BaseConfig.php","path":"SYSTEMPATH\/Config\/BaseConfig.php"},{"name":"BaseConnection.php","path":"SYSTEMPATH\/Database\/BaseConnection.php"},{"name":"BaseHandler.php","path":"SYSTEMPATH\/Cache\/Handlers\/BaseHandler.php"},{"name":"BaseHandler.php","path":"SYSTEMPATH\/Encryption\/Handlers\/BaseHandler.php"},{"name":"BaseHandler.php","path":"SYSTEMPATH\/Session\/Handlers\/BaseHandler.php"},{"name":"BaseModel.php","path":"SYSTEMPATH\/BaseModel.php"},{"name":"BaseResult.php","path":"SYSTEMPATH\/Database\/BaseResult.php"},{"name":"BaseService.php","path":"SYSTEMPATH\/Config\/BaseService.php"},{"name":"Builder.php","path":"SYSTEMPATH\/Database\/MySQLi\/Builder.php"},{"name":"CacheFactory.php","path":"SYSTEMPATH\/Cache\/CacheFactory.php"},{"name":"CacheInterface.php","path":"SYSTEMPATH\/Cache\/CacheInterface.php"},{"name":"CliRenderer.php","path":"SYSTEMPATH\/ThirdParty\/Kint\/Renderer\/CliRenderer.php"},{"name":"CloneableCookieInterface.php","path":"SYSTEMPATH\/Cookie\/CloneableCookieInterface.php"},{"name":"CodeIgniter.php","path":"SYSTEMPATH\/CodeIgniter.php"},{"name":"Common.php","path":"SYSTEMPATH\/Common.php"},{"name":"Config.php","path":"SYSTEMPATH\/Database\/Config.php"},{"name":"Connection.php","path":"SYSTEMPATH\/Database\/MySQLi\/Connection.php"},{"name":"ConnectionInterface.php","path":"SYSTEMPATH\/Database\/ConnectionInterface.php"},{"name":"ContentSecurityPolicy.php","path":"SYSTEMPATH\/HTTP\/ContentSecurityPolicy.php"},{"name":"Controller.php","path":"SYSTEMPATH\/Controller.php"},{"name":"Cookie.php","path":"SYSTEMPATH\/Cookie\/Cookie.php"},{"name":"CookieInterface.php","path":"SYSTEMPATH\/Cookie\/CookieInterface.php"},{"name":"CookieStore.php","path":"SYSTEMPATH\/Cookie\/CookieStore.php"},{"name":"Database.php","path":"SYSTEMPATH\/Database\/Database.php"},{"name":"Database.php","path":"SYSTEMPATH\/Debug\/Toolbar\/Collectors\/Database.php"},{"name":"DebugToolbar.php","path":"SYSTEMPATH\/Filters\/DebugToolbar.php"},{"name":"DotEnv.php","path":"SYSTEMPATH\/Config\/DotEnv.php"},{"name":"EncrypterInterface.php","path":"SYSTEMPATH\/Encryption\/EncrypterInterface.php"},{"name":"Encryption.php","path":"SYSTEMPATH\/Encryption\/Encryption.php"},{"name":"Escaper.php","path":"SYSTEMPATH\/ThirdParty\/Escaper\/Escaper.php"},{"name":"Events.php","path":"SYSTEMPATH\/Debug\/Toolbar\/Collectors\/Events.php"},{"name":"Events.php","path":"SYSTEMPATH\/Events\/Events.php"},{"name":"Exceptions.php","path":"SYSTEMPATH\/Debug\/Exceptions.php"},{"name":"Factories.php","path":"SYSTEMPATH\/Config\/Factories.php"},{"name":"Factory.php","path":"SYSTEMPATH\/Config\/Factory.php"},{"name":"FileHandler.php","path":"SYSTEMPATH\/Cache\/Handlers\/FileHandler.php"},{"name":"FileHandler.php","path":"SYSTEMPATH\/Session\/Handlers\/FileHandler.php"},{"name":"FileLocator.php","path":"SYSTEMPATH\/Autoloader\/FileLocator.php"},{"name":"Files.php","path":"SYSTEMPATH\/Debug\/Toolbar\/Collectors\/Files.php"},{"name":"FilterInterface.php","path":"SYSTEMPATH\/Filters\/FilterInterface.php"},{"name":"Filters.php","path":"SYSTEMPATH\/Filters\/Filters.php"},{"name":"Forge.php","path":"SYSTEMPATH\/Database\/Forge.php"},{"name":"Forge.php","path":"SYSTEMPATH\/Database\/MySQLi\/Forge.php"},{"name":"FormatRules.php","path":"SYSTEMPATH\/Validation\/FormatRules.php"},{"name":"Header.php","path":"SYSTEMPATH\/HTTP\/Header.php"},{"name":"IncomingRequest.php","path":"SYSTEMPATH\/HTTP\/IncomingRequest.php"},{"name":"Kint.php","path":"SYSTEMPATH\/ThirdParty\/Kint\/Kint.php"},{"name":"Logger.php","path":"SYSTEMPATH\/Log\/Logger.php"},{"name":"LoggerAwareTrait.php","path":"SYSTEMPATH\/ThirdParty\/PSR\/Log\/LoggerAwareTrait.php"},{"name":"LoggerInterface.php","path":"SYSTEMPATH\/ThirdParty\/PSR\/Log\/LoggerInterface.php"},{"name":"Logs.php","path":"SYSTEMPATH\/Debug\/Toolbar\/Collectors\/Logs.php"},{"name":"Message.php","path":"SYSTEMPATH\/HTTP\/Message.php"},{"name":"MessageInterface.php","path":"SYSTEMPATH\/HTTP\/MessageInterface.php"},{"name":"MessageTrait.php","path":"SYSTEMPATH\/HTTP\/MessageTrait.php"},{"name":"MigrationRunner.php","path":"SYSTEMPATH\/Database\/MigrationRunner.php"},{"name":"Model.php","path":"SYSTEMPATH\/Model.php"},{"name":"Modules.php","path":"SYSTEMPATH\/Modules\/Modules.php"},{"name":"OpenSSLHandler.php","path":"SYSTEMPATH\/Encryption\/Handlers\/OpenSSLHandler.php"},{"name":"Query.php","path":"SYSTEMPATH\/Database\/Query.php"},{"name":"QueryInterface.php","path":"SYSTEMPATH\/Database\/QueryInterface.php"},{"name":"Renderer.php","path":"SYSTEMPATH\/ThirdParty\/Kint\/Renderer\/Renderer.php"},{"name":"RendererInterface.php","path":"SYSTEMPATH\/View\/RendererInterface.php"},{"name":"Request.php","path":"SYSTEMPATH\/HTTP\/Request.php"},{"name":"RequestInterface.php","path":"SYSTEMPATH\/HTTP\/RequestInterface.php"},{"name":"RequestTrait.php","path":"SYSTEMPATH\/HTTP\/RequestTrait.php"},{"name":"Response.php","path":"SYSTEMPATH\/HTTP\/Response.php"},{"name":"ResponseInterface.php","path":"SYSTEMPATH\/HTTP\/ResponseInterface.php"},{"name":"ResponseTrait.php","path":"SYSTEMPATH\/API\/ResponseTrait.php"},{"name":"ResponseTrait.php","path":"SYSTEMPATH\/HTTP\/ResponseTrait.php"},{"name":"Result.php","path":"SYSTEMPATH\/Database\/MySQLi\/Result.php"},{"name":"ResultInterface.php","path":"SYSTEMPATH\/Database\/ResultInterface.php"},{"name":"RichRenderer.php","path":"SYSTEMPATH\/Debug\/Kint\/RichRenderer.php"},{"name":"RichRenderer.php","path":"SYSTEMPATH\/ThirdParty\/Kint\/Renderer\/RichRenderer.php"},{"name":"RouteCollection.php","path":"SYSTEMPATH\/Router\/RouteCollection.php"},{"name":"RouteCollectionInterface.php","path":"SYSTEMPATH\/Router\/RouteCollectionInterface.php"},{"name":"Router.php","path":"SYSTEMPATH\/Router\/Router.php"},{"name":"RouterInterface.php","path":"SYSTEMPATH\/Router\/RouterInterface.php"},{"name":"Routes.php","path":"SYSTEMPATH\/Config\/Routes.php"},{"name":"Routes.php","path":"SYSTEMPATH\/Debug\/Toolbar\/Collectors\/Routes.php"},{"name":"Services.php","path":"SYSTEMPATH\/Config\/Services.php"},{"name":"Session.php","path":"SYSTEMPATH\/Session\/Session.php"},{"name":"SessionInterface.php","path":"SYSTEMPATH\/Session\/SessionInterface.php"},{"name":"TextRenderer.php","path":"SYSTEMPATH\/ThirdParty\/Kint\/Renderer\/TextRenderer.php"},{"name":"Timer.php","path":"SYSTEMPATH\/Debug\/Timer.php"},{"name":"Timers.php","path":"SYSTEMPATH\/Debug\/Toolbar\/Collectors\/Timers.php"},{"name":"Toolbar.php","path":"SYSTEMPATH\/Debug\/Toolbar.php"},{"name":"URI.php","path":"SYSTEMPATH\/HTTP\/URI.php"},{"name":"UserAgent.php","path":"SYSTEMPATH\/HTTP\/UserAgent.php"},{"name":"Utils.php","path":"SYSTEMPATH\/ThirdParty\/Kint\/Utils.php"},{"name":"Validation.php","path":"SYSTEMPATH\/Validation\/Validation.php"},{"name":"ValidationInterface.php","path":"SYSTEMPATH\/Validation\/ValidationInterface.php"},{"name":"View.php","path":"SYSTEMPATH\/Config\/View.php"},{"name":"View.php","path":"SYSTEMPATH\/View\/View.php"},{"name":"Views.php","path":"SYSTEMPATH\/Debug\/Toolbar\/Collectors\/Views.php"},{"name":"array_helper.php","path":"SYSTEMPATH\/Helpers\/array_helper.php"},{"name":"bootstrap.php","path":"SYSTEMPATH\/bootstrap.php"},{"name":"cookie_helper.php","path":"SYSTEMPATH\/Helpers\/cookie_helper.php"},{"name":"date_helper.php","path":"SYSTEMPATH\/Helpers\/date_helper.php"},{"name":"filesystem_helper.php","path":"SYSTEMPATH\/Helpers\/filesystem_helper.php"},{"name":"form_helper.php","path":"SYSTEMPATH\/Helpers\/form_helper.php"},{"name":"html_helper.php","path":"SYSTEMPATH\/Helpers\/html_helper.php"},{"name":"init.php","path":"SYSTEMPATH\/ThirdParty\/Kint\/init.php"},{"name":"init_helpers.php","path":"SYSTEMPATH\/ThirdParty\/Kint\/init_helpers.php"},{"name":"text_helper.php","path":"SYSTEMPATH\/Helpers\/text_helper.php"},{"name":"url_helper.php","path":"SYSTEMPATH\/Helpers\/url_helper.php"}],"userFiles":[{"name":"Addgroupmodel.php","path":"APPPATH\/Models\/Addgroupmodel.php"},{"name":"Adminconfigurationmodel.php","path":"APPPATH\/Models\/Adminconfigurationmodel.php"},{"name":"Adminrolemodel.php","path":"APPPATH\/Models\/Adminrolemodel.php"},{"name":"Apimodel.php","path":"APPPATH\/Models\/Apimodel.php"},{"name":"App.php","path":"APPPATH\/Config\/App.php"},{"name":"Autoload.php","path":"APPPATH\/Config\/Autoload.php"},{"name":"BaseController.php","path":"APPPATH\/Controllers\/BaseController.php"},{"name":"Batchmodel.php","path":"APPPATH\/Models\/Batchmodel.php"},{"name":"Cache.php","path":"APPPATH\/Config\/Cache.php"},{"name":"Codemodel.php","path":"APPPATH\/Models\/Codemodel.php"},{"name":"Codes.php","path":"APPPATH\/Controllers\/Codes.php"},{"name":"Common.php","path":"APPPATH\/Common.php"},{"name":"Constants.php","path":"APPPATH\/Config\/Constants.php"},{"name":"ContentSecurityPolicy.php","path":"APPPATH\/Config\/ContentSecurityPolicy.php"},{"name":"Cookie.php","path":"APPPATH\/Config\/Cookie.php"},{"name":"Database.php","path":"APPPATH\/Config\/Database.php"},{"name":"Encryption.php","path":"APPPATH\/Config\/Encryption.php"},{"name":"Events.php","path":"APPPATH\/Config\/Events.php"},{"name":"Exceptions.php","path":"APPPATH\/Config\/Exceptions.php"},{"name":"Feature.php","path":"APPPATH\/Config\/Feature.php"},{"name":"Filedatamodel.php","path":"APPPATH\/Models\/Filedatamodel.php"},{"name":"Filters.php","path":"APPPATH\/Config\/Filters.php"},{"name":"Generalsettingsmodel.php","path":"APPPATH\/Models\/Generalsettingsmodel.php"},{"name":"Ipbannedmodel.php","path":"APPPATH\/Models\/Ipbannedmodel.php"},{"name":"Kint.php","path":"APPPATH\/Config\/Kint.php"},{"name":"Licensemodel.php","path":"APPPATH\/Models\/Licensemodel.php"},{"name":"Logger.php","path":"APPPATH\/Config\/Logger.php"},{"name":"Loginattemptsmodel.php","path":"APPPATH\/Models\/Loginattemptsmodel.php"},{"name":"Loginmodel.php","path":"APPPATH\/Models\/Loginmodel.php"},{"name":"Mediafilesmodel.php","path":"APPPATH\/Models\/Mediafilesmodel.php"},{"name":"Mediatagsmodel.php","path":"APPPATH\/Models\/Mediatagsmodel.php"},{"name":"Migrations.php","path":"APPPATH\/Config\/Migrations.php"},{"name":"Modules.php","path":"APPPATH\/Config\/Modules.php"},{"name":"Paths.php","path":"APPPATH\/Config\/Paths.php"},{"name":"Routes.php","path":"APPPATH\/Config\/Routes.php"},{"name":"Securitymodel.php","path":"APPPATH\/Models\/Securitymodel.php"},{"name":"Services.php","path":"APPPATH\/Config\/Services.php"},{"name":"Smtpmodel.php","path":"APPPATH\/Models\/Smtpmodel.php"},{"name":"Toolbar.php","path":"APPPATH\/Config\/Toolbar.php"},{"name":"UserAgents.php","path":"APPPATH\/Config\/UserAgents.php"},{"name":"Validation.php","path":"APPPATH\/Config\/Validation.php"},{"name":"View.php","path":"APPPATH\/Config\/View.php"},{"name":"development.php","path":"APPPATH\/Config\/Boot\/development.php"},{"name":"index.php","path":"FCPATH\/index.php"},{"name":"isLoggedIn.php","path":"APPPATH\/Filters\/isLoggedIn.php"}]},"badgeValue":154,"isEmpty":false,"hasTabContent":true,"hasLabel":false,"icon":"data:image\/png;base64,iVBORw0KGgoAAAANSUhEUgAAABgAAAAYCAYAAADgdz34AAAAAXNSR0IArs4c6QAAAARnQU1BAACxjwv8YQUAAAAJcEhZcwAADsMAAA7DAcdvqGQAAAGBSURBVEhL7ZQ9S8NQGIVTBQUncfMfCO4uLgoKbuKQOWg+OkXERRE1IAXrIHbVDrqIDuLiJgj+gro7S3dnpfq88b1FMTE3VZx64HBzzvvZWxKnj15QCcPwCD5HUfSWR+JtzgmtsUcQBEva5IIm9SwSu+95CAWbUuy67qBa32ByZEDpIaZYZSZMjjQuPcQUq8yEyYEb8FSerYeQVGbAFzJkX1PyQWLhgCz0BxTCekC1Wp0hsa6yokzhed4oje6Iz6rlJEkyIKfUEFtITVtQdAibn5rMyaYsMS+a5wTv8qeXMhcU16QZbKgl3hbs+L4\/pnpdc87MElZgq10p5DxGdq8I7xrvUWUKvG3NbSK7ubngYzdJwSsF7TiOh9VOgfcEz1UayNe3JUPM1RWC5GXYgTfc75B4NBmXJnAtTfpABX0iPvEd9ezALwkplCFXcr9styiNOKc1RRZpaPM9tcqBwlWzGY1qPL9wjqRBgF5BH6j8HWh2S7MHlX8PrmbK+k\/8PzjOOzx1D3i1pKTTAAAAAElFTkSuQmCC","hasTimelineData":false,"timelineData":[]},{"title":"Routes","titleSafe":"routes","titleDetails":"","display":{"matchedRoute":[{"directory":"","controller":"\\App\\Controllers\\Codes","method":"getcodeslist","paramCount":0,"truePCount":0,"params":[]}],"routes":[{"method":"GET","route":"\/","handler":"\\App\\Controllers\\Login::login"},{"method":"GET","route":"banned","handler":"\\App\\Controllers\\Banned::banned"},{"method":"GET","route":"test","handler":"\\App\\Controllers\\Testing::test"},{"method":"GET","route":"geneartenewcodes","handler":"\\App\\Controllers\\Codes::geneartenewcodes"},{"method":"GET","route":"editfile\/([0-9]+)","handler":"\\App\\Controllers\\Codes::editfile\/$1"},{"method":"GET","route":"listgroups","handler":"\\App\\Controllers\\Addgroup::listgroups"},{"method":"GET","route":"adminconfiguration","handler":"\\App\\Controllers\\Adminconfiguration::adminconfiguration"},{"method":"GET","route":"api","handler":"\\App\\Controllers\\Api::api"},{"method":"GET","route":"login","handler":"\\App\\Controllers\\Login::login"},{"method":"GET","route":"profile","handler":"\\App\\Controllers\\Profile::profile"},{"method":"GET","route":"settings","handler":"\\App\\Controllers\\Settings::settings"},{"method":"GET","route":"generalsettings","handler":"\\App\\Controllers\\Settings::generalsettings"},{"method":"GET","route":"smtpsettings","handler":"\\App\\Controllers\\Settings::smtpsettings"},{"method":"GET","route":"addvertisement","handler":"\\App\\Controllers\\Addvertisement::addvertisement"},{"method":"GET","route":"logout","handler":"\\App\\Controllers\\Logout::logout"},{"method":"GET","route":"dashboard","handler":"\\App\\Controllers\\Dashboard::dashboard"},{"method":"GET","route":"addsrecords","handler":"\\App\\Controllers\\Addsrecords::addsrecords"},{"method":"GET","route":"editadd\/([0-9]+)","handler":"\\App\\Controllers\\Addsrecords::editadd\/$1"},{"method":"GET","route":"changeorderbyid","handler":"\\App\\Controllers\\Addsrecords::changeorderbyid"},{"method":"GET","route":"generateapi","handler":"\\App\\Controllers\\Generateapi::generateapi"},{"method":"GET","route":"codes","handler":"\\App\\Controllers\\Codes::codes"},{"method":"GET","route":"managerecords\/([0-9]+)","handler":"\\App\\Controllers\\Codes::managerecords\/$1"},{"method":"GET","route":"deleterecords\/([0-9]+)","handler":"\\App\\Controllers\\Codes::deleterecords\/$1"},{"method":"GET","route":"addcodes\/([0-9]+)","handler":"\\App\\Controllers\\Codes::addcodes\/$1"},{"method":"GET","route":"addgroup","handler":"\\App\\Controllers\\Addgroup::addgroup"},{"method":"GET","route":"editgroup\/([0-9]+)","handler":"\\App\\Controllers\\Addgroup::editgroup\/$1"},{"method":"GET","route":"configurelicense","handler":"\\App\\Controllers\\License::configurelicense"},{"method":"GET","route":"unblockips","handler":"\\App\\Controllers\\Unblockips::unblockips"},{"method":"HEAD","route":"adminconfiguration","handler":"\\App\\Controllers\\Adminconfiguration::adminconfiguration"},{"method":"HEAD","route":"api","handler":"\\App\\Controllers\\Api::api"},{"method":"HEAD","route":"login","handler":"\\App\\Controllers\\Login::login"},{"method":"HEAD","route":"profile","handler":"\\App\\Controllers\\Profile::profile"},{"method":"HEAD","route":"settings","handler":"\\App\\Controllers\\Settings::settings"},{"method":"HEAD","route":"generalsettings","handler":"\\App\\Controllers\\Settings::generalsettings"},{"method":"HEAD","route":"smtpsettings","handler":"\\App\\Controllers\\Settings::smtpsettings"},{"method":"HEAD","route":"addvertisement","handler":"\\App\\Controllers\\Addvertisement::addvertisement"},{"method":"HEAD","route":"logout","handler":"\\App\\Controllers\\Logout::logout"},{"method":"HEAD","route":"dashboard","handler":"\\App\\Controllers\\Dashboard::dashboard"},{"method":"HEAD","route":"addsrecords","handler":"\\App\\Controllers\\Addsrecords::addsrecords"},{"method":"HEAD","route":"editadd\/([0-9]+)","handler":"\\App\\Controllers\\Addsrecords::editadd\/$1"},{"method":"HEAD","route":"changeorderbyid","handler":"\\App\\Controllers\\Addsrecords::changeorderbyid"},{"method":"HEAD","route":"generateapi","handler":"\\App\\Controllers\\Generateapi::generateapi"},{"method":"HEAD","route":"codes","handler":"\\App\\Controllers\\Codes::codes"},{"method":"HEAD","route":"managerecords\/([0-9]+)","handler":"\\App\\Controllers\\Codes::managerecords\/$1"},{"method":"HEAD","route":"deleterecords\/([0-9]+)","handler":"\\App\\Controllers\\Codes::deleterecords\/$1"},{"method":"HEAD","route":"addcodes\/([0-9]+)","handler":"\\App\\Controllers\\Codes::addcodes\/$1"},{"method":"HEAD","route":"addgroup","handler":"\\App\\Controllers\\Addgroup::addgroup"},{"method":"HEAD","route":"editgroup\/([0-9]+)","handler":"\\App\\Controllers\\Addgroup::editgroup\/$1"},{"method":"HEAD","route":"configurelicense","handler":"\\App\\Controllers\\License::configurelicense"},{"method":"HEAD","route":"unblockips","handler":"\\App\\Controllers\\Unblockips::unblockips"},{"method":"POST","route":"sendmailtoadmin","handler":"\\App\\Controllers\\Generateapi::sendmailtoadmin"},{"method":"POST","route":"confirmationadminpassword","handler":"\\App\\Controllers\\BaseController::confirmationadminpassword"},{"method":"POST","route":"processingcodes","handler":"\\App\\Controllers\\Codes::processingcodes"},{"method":"POST","route":"loopcodesprocess","handler":"\\App\\Controllers\\Codes::loopcodesprocess"},{"method":"POST","route":"load-data-for-list","handler":"\\App\\Controllers\\Codes::loaddatafortable"},{"method":"POST","route":"updaterecords\/([0-9]+)","handler":"\\App\\Controllers\\Codes::updaterecords\/$1"},{"method":"POST","route":"editfiledataprocessing","handler":"\\App\\Controllers\\Files::editfiledataprocessing"},{"method":"POST","route":"get-codes-list","handler":"\\App\\Controllers\\Codes::getcodeslist"},{"method":"POST","route":"deletefiledata","handler":"\\App\\Controllers\\Files::deletefiledata"},{"method":"POST","route":"addcodestofile","handler":"\\App\\Controllers\\Codes::addcodestofile"},{"method":"POST","route":"loade-data","handler":"\\App\\Controllers\\Addgroup::loaddataforgrouptbl"},{"method":"POST","route":"checkgroupexitsbeforedelete","handler":"\\App\\Controllers\\Addgroup::checkgroupexitsbeforedelete"},{"method":"POST","route":"deletefilegroupdata","handler":"\\App\\Controllers\\Addgroup::deletefilegroupdata"},{"method":"POST","route":"removelogo","handler":"\\App\\Controllers\\Settings::removelogo"},{"method":"POST","route":"createcsv","handler":"\\App\\Controllers\\Codes::createcsv"},{"method":"POST","route":"deletecodes","handler":"\\App\\Controllers\\Codes::deletecodes"},{"method":"POST","route":"blockipslist","handler":"\\App\\Controllers\\Unblockips::blockipslist"},{"method":"POST","route":"deletemultipalips","handler":"\\App\\Controllers\\Unblockips::deletemultipalips"},{"method":"POST","route":"adminconfiguration","handler":"\\App\\Controllers\\Adminconfiguration::adminconfiguration"},{"method":"POST","route":"api","handler":"\\App\\Controllers\\Api::api"},{"method":"POST","route":"login","handler":"\\App\\Controllers\\Login::login"},{"method":"POST","route":"profile","handler":"\\App\\Controllers\\Profile::profile"},{"method":"POST","route":"settings","handler":"\\App\\Controllers\\Settings::settings"},{"method":"POST","route":"generalsettings","handler":"\\App\\Controllers\\Settings::generalsettings"},{"method":"POST","route":"smtpsettings","handler":"\\App\\Controllers\\Settings::smtpsettings"},{"method":"POST","route":"addvertisement","handler":"\\App\\Controllers\\Addvertisement::addvertisement"},{"method":"POST","route":"logout","handler":"\\App\\Controllers\\Logout::logout"},{"method":"POST","route":"dashboard","handler":"\\App\\Controllers\\Dashboard::dashboard"},{"method":"POST","route":"addsrecords","handler":"\\App\\Controllers\\Addsrecords::addsrecords"},{"method":"POST","route":"editadd\/([0-9]+)","handler":"\\App\\Controllers\\Addsrecords::editadd\/$1"},{"method":"POST","route":"changeorderbyid","handler":"\\App\\Controllers\\Addsrecords::changeorderbyid"},{"method":"POST","route":"generateapi","handler":"\\App\\Controllers\\Generateapi::generateapi"},{"method":"POST","route":"codes","handler":"\\App\\Controllers\\Codes::codes"},{"method":"POST","route":"managerecords\/([0-9]+)","handler":"\\App\\Controllers\\Codes::managerecords\/$1"},{"method":"POST","route":"deleterecords\/([0-9]+)","handler":"\\App\\Controllers\\Codes::deleterecords\/$1"},{"method":"POST","route":"addcodes\/([0-9]+)","handler":"\\App\\Controllers\\Codes::addcodes\/$1"},{"method":"POST","route":"addgroup","handler":"\\App\\Controllers\\Addgroup::addgroup"},{"method":"POST","route":"editgroup\/([0-9]+)","handler":"\\App\\Controllers\\Addgroup::editgroup\/$1"},{"method":"POST","route":"configurelicense","handler":"\\App\\Controllers\\License::configurelicense"},{"method":"POST","route":"unblockips","handler":"\\App\\Controllers\\Unblockips::unblockips"},{"method":"PUT","route":"adminconfiguration","handler":"\\App\\Controllers\\Adminconfiguration::adminconfiguration"},{"method":"PUT","route":"api","handler":"\\App\\Controllers\\Api::api"},{"method":"PUT","route":"login","handler":"\\App\\Controllers\\Login::login"},{"method":"PUT","route":"profile","handler":"\\App\\Controllers\\Profile::profile"},{"method":"PUT","route":"settings","handler":"\\App\\Controllers\\Settings::settings"},{"method":"PUT","route":"generalsettings","handler":"\\App\\Controllers\\Settings::generalsettings"},{"method":"PUT","route":"smtpsettings","handler":"\\App\\Controllers\\Settings::smtpsettings"},{"method":"PUT","route":"addvertisement","handler":"\\App\\Controllers\\Addvertisement::addvertisement"},{"method":"PUT","route":"logout","handler":"\\App\\Controllers\\Logout::logout"},{"method":"PUT","route":"dashboard","handler":"\\App\\Controllers\\Dashboard::dashboard"},{"method":"PUT","route":"addsrecords","handler":"\\App\\Controllers\\Addsrecords::addsrecords"},{"method":"PUT","route":"editadd\/([0-9]+)","handler":"\\App\\Controllers\\Addsrecords::editadd\/$1"},{"method":"PUT","route":"changeorderbyid","handler":"\\App\\Controllers\\Addsrecords::changeorderbyid"},{"method":"PUT","route":"generateapi","handler":"\\App\\Controllers\\Generateapi::generateapi"},{"method":"PUT","route":"codes","handler":"\\App\\Controllers\\Codes::codes"},{"method":"PUT","route":"managerecords\/([0-9]+)","handler":"\\App\\Controllers\\Codes::managerecords\/$1"},{"method":"PUT","route":"deleterecords\/([0-9]+)","handler":"\\App\\Controllers\\Codes::deleterecords\/$1"},{"method":"PUT","route":"addcodes\/([0-9]+)","handler":"\\App\\Controllers\\Codes::addcodes\/$1"},{"method":"PUT","route":"addgroup","handler":"\\App\\Controllers\\Addgroup::addgroup"},{"method":"PUT","route":"editgroup\/([0-9]+)","handler":"\\App\\Controllers\\Addgroup::editgroup\/$1"},{"method":"PUT","route":"configurelicense","handler":"\\App\\Controllers\\License::configurelicense"},{"method":"PUT","route":"unblockips","handler":"\\App\\Controllers\\Unblockips::unblockips"},{"method":"DELETE","route":"adminconfiguration","handler":"\\App\\Controllers\\Adminconfiguration::adminconfiguration"},{"method":"DELETE","route":"api","handler":"\\App\\Controllers\\Api::api"},{"method":"DELETE","route":"login","handler":"\\App\\Controllers\\Login::login"},{"method":"DELETE","route":"profile","handler":"\\App\\Controllers\\Profile::profile"},{"method":"DELETE","route":"settings","handler":"\\App\\Controllers\\Settings::settings"},{"method":"DELETE","route":"generalsettings","handler":"\\App\\Controllers\\Settings::generalsettings"},{"method":"DELETE","route":"smtpsettings","handler":"\\App\\Controllers\\Settings::smtpsettings"},{"method":"DELETE","route":"addvertisement","handler":"\\App\\Controllers\\Addvertisement::addvertisement"},{"method":"DELETE","route":"logout","handler":"\\App\\Controllers\\Logout::logout"},{"method":"DELETE","route":"dashboard","handler":"\\App\\Controllers\\Dashboard::dashboard"},{"method":"DELETE","route":"addsrecords","handler":"\\App\\Controllers\\Addsrecords::addsrecords"},{"method":"DELETE","route":"editadd\/([0-9]+)","handler":"\\App\\Controllers\\Addsrecords::editadd\/$1"},{"method":"DELETE","route":"changeorderbyid","handler":"\\App\\Controllers\\Addsrecords::changeorderbyid"},{"method":"DELETE","route":"generateapi","handler":"\\App\\Controllers\\Generateapi::generateapi"},{"method":"DELETE","route":"codes","handler":"\\App\\Controllers\\Codes::codes"},{"method":"DELETE","route":"managerecords\/([0-9]+)","handler":"\\App\\Controllers\\Codes::managerecords\/$1"},{"method":"DELETE","route":"deleterecords\/([0-9]+)","handler":"\\App\\Controllers\\Codes::deleterecords\/$1"},{"method":"DELETE","route":"addcodes\/([0-9]+)","handler":"\\App\\Controllers\\Codes::addcodes\/$1"},{"method":"DELETE","route":"addgroup","handler":"\\App\\Controllers\\Addgroup::addgroup"},{"method":"DELETE","route":"editgroup\/([0-9]+)","handler":"\\App\\Controllers\\Addgroup::editgroup\/$1"},{"method":"DELETE","route":"configurelicense","handler":"\\App\\Controllers\\License::configurelicense"},{"method":"DELETE","route":"unblockips","handler":"\\App\\Controllers\\Unblockips::unblockips"},{"method":"OPTIONS","route":"adminconfiguration","handler":"\\App\\Controllers\\Adminconfiguration::adminconfiguration"},{"method":"OPTIONS","route":"api","handler":"\\App\\Controllers\\Api::api"},{"method":"OPTIONS","route":"login","handler":"\\App\\Controllers\\Login::login"},{"method":"OPTIONS","route":"profile","handler":"\\App\\Controllers\\Profile::profile"},{"method":"OPTIONS","route":"settings","handler":"\\App\\Controllers\\Settings::settings"},{"method":"OPTIONS","route":"generalsettings","handler":"\\App\\Controllers\\Settings::generalsettings"},{"method":"OPTIONS","route":"smtpsettings","handler":"\\App\\Controllers\\Settings::smtpsettings"},{"method":"OPTIONS","route":"addvertisement","handler":"\\App\\Controllers\\Addvertisement::addvertisement"},{"method":"OPTIONS","route":"logout","handler":"\\App\\Controllers\\Logout::logout"},{"method":"OPTIONS","route":"dashboard","handler":"\\App\\Controllers\\Dashboard::dashboard"},{"method":"OPTIONS","route":"addsrecords","handler":"\\App\\Controllers\\Addsrecords::addsrecords"},{"method":"OPTIONS","route":"editadd\/([0-9]+)","handler":"\\App\\Controllers\\Addsrecords::editadd\/$1"},{"method":"OPTIONS","route":"changeorderbyid","handler":"\\App\\Controllers\\Addsrecords::changeorderbyid"},{"method":"OPTIONS","route":"generateapi","handler":"\\App\\Controllers\\Generateapi::generateapi"},{"method":"OPTIONS","route":"codes","handler":"\\App\\Controllers\\Codes::codes"},{"method":"OPTIONS","route":"managerecords\/([0-9]+)","handler":"\\App\\Controllers\\Codes::managerecords\/$1"},{"method":"OPTIONS","route":"deleterecords\/([0-9]+)","handler":"\\App\\Controllers\\Codes::deleterecords\/$1"},{"method":"OPTIONS","route":"addcodes\/([0-9]+)","handler":"\\App\\Controllers\\Codes::addcodes\/$1"},{"method":"OPTIONS","route":"addgroup","handler":"\\App\\Controllers\\Addgroup::addgroup"},{"method":"OPTIONS","route":"editgroup\/([0-9]+)","handler":"\\App\\Controllers\\Addgroup::editgroup\/$1"},{"method":"OPTIONS","route":"configurelicense","handler":"\\App\\Controllers\\License::configurelicense"},{"method":"OPTIONS","route":"unblockips","handler":"\\App\\Controllers\\Unblockips::unblockips"},{"method":"TRACE","route":"adminconfiguration","handler":"\\App\\Controllers\\Adminconfiguration::adminconfiguration"},{"method":"TRACE","route":"api","handler":"\\App\\Controllers\\Api::api"},{"method":"TRACE","route":"login","handler":"\\App\\Controllers\\Login::login"},{"method":"TRACE","route":"profile","handler":"\\App\\Controllers\\Profile::profile"},{"method":"TRACE","route":"settings","handler":"\\App\\Controllers\\Settings::settings"},{"method":"TRACE","route":"generalsettings","handler":"\\App\\Controllers\\Settings::generalsettings"},{"method":"TRACE","route":"smtpsettings","handler":"\\App\\Controllers\\Settings::smtpsettings"},{"method":"TRACE","route":"addvertisement","handler":"\\App\\Controllers\\Addvertisement::addvertisement"},{"method":"TRACE","route":"logout","handler":"\\App\\Controllers\\Logout::logout"},{"method":"TRACE","route":"dashboard","handler":"\\App\\Controllers\\Dashboard::dashboard"},{"method":"TRACE","route":"addsrecords","handler":"\\App\\Controllers\\Addsrecords::addsrecords"},{"method":"TRACE","route":"editadd\/([0-9]+)","handler":"\\App\\Controllers\\Addsrecords::editadd\/$1"},{"method":"TRACE","route":"changeorderbyid","handler":"\\App\\Controllers\\Addsrecords::changeorderbyid"},{"method":"TRACE","route":"generateapi","handler":"\\App\\Controllers\\Generateapi::generateapi"},{"method":"TRACE","route":"codes","handler":"\\App\\Controllers\\Codes::codes"},{"method":"TRACE","route":"managerecords\/([0-9]+)","handler":"\\App\\Controllers\\Codes::managerecords\/$1"},{"method":"TRACE","route":"deleterecords\/([0-9]+)","handler":"\\App\\Controllers\\Codes::deleterecords\/$1"},{"method":"TRACE","route":"addcodes\/([0-9]+)","handler":"\\App\\Controllers\\Codes::addcodes\/$1"},{"method":"TRACE","route":"addgroup","handler":"\\App\\Controllers\\Addgroup::addgroup"},{"method":"TRACE","route":"editgroup\/([0-9]+)","handler":"\\App\\Controllers\\Addgroup::editgroup\/$1"},{"method":"TRACE","route":"configurelicense","handler":"\\App\\Controllers\\License::configurelicense"},{"method":"TRACE","route":"unblockips","handler":"\\App\\Controllers\\Unblockips::unblockips"},{"method":"CONNECT","route":"adminconfiguration","handler":"\\App\\Controllers\\Adminconfiguration::adminconfiguration"},{"method":"CONNECT","route":"api","handler":"\\App\\Controllers\\Api::api"},{"method":"CONNECT","route":"login","handler":"\\App\\Controllers\\Login::login"},{"method":"CONNECT","route":"profile","handler":"\\App\\Controllers\\Profile::profile"},{"method":"CONNECT","route":"settings","handler":"\\App\\Controllers\\Settings::settings"},{"method":"CONNECT","route":"generalsettings","handler":"\\App\\Controllers\\Settings::generalsettings"},{"method":"CONNECT","route":"smtpsettings","handler":"\\App\\Controllers\\Settings::smtpsettings"},{"method":"CONNECT","route":"addvertisement","handler":"\\App\\Controllers\\Addvertisement::addvertisement"},{"method":"CONNECT","route":"logout","handler":"\\App\\Controllers\\Logout::logout"},{"method":"CONNECT","route":"dashboard","handler":"\\App\\Controllers\\Dashboard::dashboard"},{"method":"CONNECT","route":"addsrecords","handler":"\\App\\Controllers\\Addsrecords::addsrecords"},{"method":"CONNECT","route":"editadd\/([0-9]+)","handler":"\\App\\Controllers\\Addsrecords::editadd\/$1"},{"method":"CONNECT","route":"changeorderbyid","handler":"\\App\\Controllers\\Addsrecords::changeorderbyid"},{"method":"CONNECT","route":"generateapi","handler":"\\App\\Controllers\\Generateapi::generateapi"},{"method":"CONNECT","route":"codes","handler":"\\App\\Controllers\\Codes::codes"},{"method":"CONNECT","route":"managerecords\/([0-9]+)","handler":"\\App\\Controllers\\Codes::managerecords\/$1"},{"method":"CONNECT","route":"deleterecords\/([0-9]+)","handler":"\\App\\Controllers\\Codes::deleterecords\/$1"},{"method":"CONNECT","route":"addcodes\/([0-9]+)","handler":"\\App\\Controllers\\Codes::addcodes\/$1"},{"method":"CONNECT","route":"addgroup","handler":"\\App\\Controllers\\Addgroup::addgroup"},{"method":"CONNECT","route":"editgroup\/([0-9]+)","handler":"\\App\\Controllers\\Addgroup::editgroup\/$1"},{"method":"CONNECT","route":"configurelicense","handler":"\\App\\Controllers\\License::configurelicense"},{"method":"CONNECT","route":"unblockips","handler":"\\App\\Controllers\\Unblockips::unblockips"},{"method":"CLI","route":"migrations\/([^\/]+)\/([^\/]+)","handler":"\\CodeIgniter\\Commands\\MigrationsCommand::$1\/$2"},{"method":"CLI","route":"migrations\/([^\/]+)","handler":"\\CodeIgniter\\Commands\\MigrationsCommand::$1"},{"method":"CLI","route":"migrations","handler":"\\CodeIgniter\\Commands\\MigrationsCommand::index"},{"method":"CLI","route":"ci(.*)","handler":"\\CodeIgniter\\CLI\\CommandRunner::index\/$1"},{"method":"CLI","route":"adminconfiguration","handler":"\\App\\Controllers\\Adminconfiguration::adminconfiguration"},{"method":"CLI","route":"api","handler":"\\App\\Controllers\\Api::api"},{"method":"CLI","route":"login","handler":"\\App\\Controllers\\Login::login"},{"method":"CLI","route":"profile","handler":"\\App\\Controllers\\Profile::profile"},{"method":"CLI","route":"settings","handler":"\\App\\Controllers\\Settings::settings"},{"method":"CLI","route":"generalsettings","handler":"\\App\\Controllers\\Settings::generalsettings"},{"method":"CLI","route":"smtpsettings","handler":"\\App\\Controllers\\Settings::smtpsettings"},{"method":"CLI","route":"addvertisement","handler":"\\App\\Controllers\\Addvertisement::addvertisement"},{"method":"CLI","route":"logout","handler":"\\App\\Controllers\\Logout::logout"},{"method":"CLI","route":"dashboard","handler":"\\App\\Controllers\\Dashboard::dashboard"},{"method":"CLI","route":"addsrecords","handler":"\\App\\Controllers\\Addsrecords::addsrecords"},{"method":"CLI","route":"editadd\/([0-9]+)","handler":"\\App\\Controllers\\Addsrecords::editadd\/$1"},{"method":"CLI","route":"changeorderbyid","handler":"\\App\\Controllers\\Addsrecords::changeorderbyid"},{"method":"CLI","route":"generateapi","handler":"\\App\\Controllers\\Generateapi::generateapi"},{"method":"CLI","route":"codes","handler":"\\App\\Controllers\\Codes::codes"},{"method":"CLI","route":"managerecords\/([0-9]+)","handler":"\\App\\Controllers\\Codes::managerecords\/$1"},{"method":"CLI","route":"deleterecords\/([0-9]+)","handler":"\\App\\Controllers\\Codes::deleterecords\/$1"},{"method":"CLI","route":"addcodes\/([0-9]+)","handler":"\\App\\Controllers\\Codes::addcodes\/$1"},{"method":"CLI","route":"addgroup","handler":"\\App\\Controllers\\Addgroup::addgroup"},{"method":"CLI","route":"editgroup\/([0-9]+)","handler":"\\App\\Controllers\\Addgroup::editgroup\/$1"},{"method":"CLI","route":"configurelicense","handler":"\\App\\Controllers\\License::configurelicense"},{"method":"CLI","route":"unblockips","handler":"\\App\\Controllers\\Unblockips::unblockips"}]},"badgeValue":42,"isEmpty":false,"hasTabContent":true,"hasLabel":false,"icon":"data:image\/png;base64,iVBORw0KGgoAAAANSUhEUgAAABgAAAAYCAYAAADgdz34AAAAAXNSR0IArs4c6QAAAARnQU1BAACxjwv8YQUAAAAJcEhZcwAADsMAAA7DAcdvqGQAAAFDSURBVEhL7ZRNSsNQFIUjVXSiOFEcuQIHDpzpxC0IGYeE\/BEInbWlCHEDLsSiuANdhKDjgm6ggtSJ+l25ldrmmTwIgtgDh\/t37r1J+16cX0dRFMtpmu5pWAkrvYjjOB7AETzStBFW+inxu3KUJMmhludQpoflS1zXban4LYqiO224h6VLTHr8Z+z8EpIHFF9gG78nDVmW7UgTHKjsCyY98QP+pcq+g8Ku2s8G8X3f3\/I8b038WZTp+bO38zxfFd+I6YY6sNUvFlSDk9CRhiAI1jX1I9Cfw7GG1UB8LAuwbU0ZwQnbRDeEN5qqBxZMLtE1ti9LtbREnMIuOXnyIf5rGIb7Wq8HmlZgwYBH7ORTcKH5E4mpjeGt9fBZcHE2GCQ3Vt7oTNPNg+FXLHnSsHkw\/FR+Gg2bB8Ptzrst\/v6C\/wrH+QB+duli6MYJdQAAAABJRU5ErkJggg==","hasTimelineData":false,"timelineData":[]},{"title":"Events","titleSafe":"events","titleDetails":"","display":{"events":{"pre_system":{"event":"pre_system","duration":"5.97","count":1},"dbquery":{"event":"dbquery","duration":"0.39","count":9}}},"badgeValue":10,"isEmpty":false,"hasTabContent":true,"hasLabel":false,"icon":"data:image\/png;base64,iVBORw0KGgoAAAANSUhEUgAAABgAAAAYCAYAAADgdz34AAAAAXNSR0IArs4c6QAAAARnQU1BAACxjwv8YQUAAAAJcEhZcwAADsMAAA7DAcdvqGQAAAEASURBVEhL7ZXNDcIwDIVTsRBH1uDQDdquUA6IM1xgCA6MwJUN2hk6AQzAz0vl0ETUxC5VT3zSU5w81\/mRMGZysixbFEVR0jSKNt8geQU9aRpFmp\/keX6AbjZ5oB74vsaN5lSzA4tLSjpBFxsjeSuRy4d2mDdQTWU7YLbXTNN05mKyovj5KL6B7q3hoy3KwdZxBlT+Ipz+jPHrBqOIynZgcZonoukb\/0ckiTHqNvDXtXEAaygRbaB9FvUTjRUHsIYS0QaSp+Dw6wT4hiTmYHOcYZsdLQ2CbXa4ftuuYR4x9vYZgdb4vsFYUdmABMYeukK9\/SUme3KMFQ77+Yfzh8eYF8+orDuDWU5LAAAAAElFTkSuQmCC","hasTimelineData":false,"timelineData":[]}],"vars":{"varData":{"View Data":[]},"session":{"__ci_last_regenerate":"<pre>1662697963<\/pre>","firstname":"smarter","adminid":"1","_ci_previous_url":"https:\/\/hosting.iptvbillingsolution.com\/finalsca\/managerecords\/3"},"post":{"draw":"15","columns":"<pre>Array\n(\n    [0] =&gt; Array\n        (\n            [data] =&gt; checkbox\n            [name] =&gt; \n            [searchable] =&gt; false\n            [orderable] =&gt; false\n            [search] =&gt; Array\n                (\n                    [value] =&gt; \n                    [regex] =&gt; false\n                )\n\n        )\n\n    [1] =&gt; Array\n        (\n            [data] =&gt; id\n            [name] =&gt; \n            [searchable] =&gt; true\n            [orderable] =&gt; true\n            [search] =&gt; Array\n                (\n                    [value] =&gt; \n                    [regex] =&gt; false\n                )\n\n        )\n\n    [2] =&gt; Array\n        (\n            [data] =&gt; activationcode\n            [name] =&gt; \n            [searchable] =&gt; true\n            [orderable] =&gt; false\n            [search] =&gt; Array\n                (\n                    [value] =&gt; \n                    [regex] =&gt; false\n                )\n\n        )\n\n    [3] =&gt; Array\n        (\n            [data] =&gt; status\n            [name] =&gt; \n            [searchable] =&gt; true\n            [orderable] =&gt; false\n            [search] =&gt; Array\n                (\n                    [value] =&gt; \n                    [regex] =&gt; false\n                )\n\n        )\n\n    [4] =&gt; Array\n        (\n            [data] =&gt; formatted_activationdate\n            [name] =&gt; \n            [searchable] =&gt; true\n            [orderable] =&gt; false\n            [search] =&gt; Array\n                (\n                    [value] =&gt; \n                    [regex] =&gt; false\n                )\n\n        )\n\n    [5] =&gt; Array\n        (\n            [data] =&gt; formatted_createddate\n            [name] =&gt; \n            [searchable] =&gt; true\n            [orderable] =&gt; false\n            [search] =&gt; Array\n                (\n                    [value] =&gt; \n                    [regex] =&gt; false\n                )\n\n        )\n\n)\n<\/pre>","order":"<pre>Array\n(\n    [0] =&gt; Array\n        (\n            [column] =&gt; 1\n            [dir] =&gt; desc\n        )\n\n)\n<\/pre>","start":"0","length":"10","search":"<pre>Array\n(\n    [value] =&gt; \n    [regex] =&gt; false\n)\n<\/pre>","fieldid":"3","filterformdata":""},"headers":{"Content-Type":"application\/x-www-form-urlencoded; charset=UTF-8","Host":"hosting.iptvbillingsolution.com","Connection":"keep-alive","Sec-Ch-Ua":"&quot;Google Chrome&quot;;v=&quot;105&quot;, &quot;Not)A;Brand&quot;;v=&quot;8&quot;, &quot;Chromium&quot;;v=&quot;105&quot;","Accept":"application\/json, text\/javascript, *\/*; q=0.01","X-Requested-With":"XMLHttpRequest","Sec-Ch-Ua-Mobile":"?0","User-Agent":"Mozilla\/5.0 (Windows NT 10.0; Win64; x64) AppleWebKit\/537.36 (KHTML, like Gecko) Chrome\/105.0.0.0 Safari\/537.36","Sec-Ch-Ua-Platform":"&quot;Windows&quot;","Origin":"https:\/\/hosting.iptvbillingsolution.com","Sec-Fetch-Site":"same-origin","Sec-Fetch-Mode":"cors","Sec-Fetch-Dest":"empty","Referer":"https:\/\/hosting.iptvbillingsolution.com\/finalsca\/managerecords\/3","Accept-Encoding":"gzip, deflate, br","Accept-Language":"en-US,en;q=0.9","Cookie":"email=smarter.panel%40gmail.com; password=lbkJcub5Z3ceN24GdAaR34m9M1rknVU95LeSH6dVWnfpT5Fk3547F8gPzHhLtUHCd6ORs4Hubg%2FkRObnyWuQAEeXqy6pifr5gQrAh1R1ADGsXv92JRrx99N%2FRRXIjOqZ59PBPCtodA%3D%3D; ci_session=ud6bhludm9s0naoklr5ji9e5i4eco1uu; csrf_cookie_name=72568322b327cbf8df0e96dd778339f3"},"cookies":{"email":"smarter.panel@gmail.com","password":"lbkJcub5Z3ceN24GdAaR34m9M1rknVU95LeSH6dVWnfpT5Fk3547F8gPzHhLtUHCd6ORs4Hubg\/kRObnyWuQAEeXqy6pifr5gQrAh1R1ADGsXv92JRrx99N\/RRXIjOqZ59PBPCtodA==","ci_session":"ud6bhludm9s0naoklr5ji9e5i4eco1uu","csrf_cookie_name":"72568322b327cbf8df0e96dd778339f3"},"request":"HTTPS\/1.1","response":{"statusCode":200,"reason":"OK","contentType":"text\/html; charset=UTF-8"}},"config":{"ciVersion":"4.1.7","phpVersion":"7.4.28","phpSAPI":"apache2handler","environment":"development","baseURL":"https:\/\/hosting.iptvbillingsolution.com\/finalsca\/","timezone":"America\/Chicago","locale":"en","cspEnabled":false}}